puppet_env_manager/__init__.py
puppet_env_manager/config.py
puppet_env_manager/exceptions.py
puppet_env_manager/manager.py
puppet_env_manager-0.4.5.data/scripts/puppet-env-manager
puppet_env_manager-0.4.5.dist-info/METADATA
puppet_env_manager-0.4.5.dist-info/WHEEL
puppet_env_manager-0.4.5.dist-info/top_level.txt
puppet_env_manager-0.4.5.dist-info/RECORD
